pyuf/__init__.py
pyuf/pyuf.py
pyuf-0.1.2.dist-info/LICENSE
pyuf-0.1.2.dist-info/METADATA
pyuf-0.1.2.dist-info/WHEEL
pyuf-0.1.2.dist-info/top_level.txt
pyuf-0.1.2.dist-info/RECORD
